demarc/__cli__.py
demarc/__init__.py
demarc/_version.py
demarc/conf/__init__.py
demarc/conf/about/demarc.yaml
demarc/py.typed
demarc-0.1.0.dist-info/LICENSE
demarc-0.1.0.dist-info/METADATA
demarc-0.1.0.dist-info/WHEEL
demarc-0.1.0.dist-info/entry_points.txt
demarc-0.1.0.dist-info/RECORD
