Metadata-Version: 2.1
Name: demarc
Version: 0.1.0
Summary: A Python package for Deceptive Marketing Classification.
Home-page: https://demarc.entelecheia.ai
License: MIT
Author: Young Joon Lee
Author-email: entelecheia@hotmail.com
Requires-Python: >=3.9,<3.13
Classifier: License :: OSI Approved :: MIT License
Classifier: Programming Language :: Python :: 3
Classifier: Programming Language :: Python :: 3.9
Classifier: Programming Language :: Python :: 3.10
Classifier: Programming Language :: Python :: 3.11
Classifier: Programming Language :: Python :: 3.12
Requires-Dist: click (>=8.1.3,<9.0.0)
Requires-Dist: hyfi (>=1.36.3,<2.0.0)
Project-URL: Repository, https://github.com/entelecheia/demarc
